django_q_sentry/__init__.py
django_q_sentry/sentry.py
django_q_sentry-0.1.6.dist-info/LICENSE.txt
django_q_sentry-0.1.6.dist-info/METADATA
django_q_sentry-0.1.6.dist-info/WHEEL
django_q_sentry-0.1.6.dist-info/top_level.txt
django_q_sentry-0.1.6.dist-info/RECORD
