Metadata-Version: 2.1
Name: django-q-sentry
Version: 0.1.6
Summary: A Sentry support plugin for Django Q
Home-page: https://django-q.readthedocs.org
Author: Daniel Welch, Christo Goosen
Author-email: dwelch2102@gmail.com, christogoosen@gmail.com
License: MIT
Keywords: django distributed task queue worker scheduler cron redis disque ironmq sqs orm mongodb multiprocessing sentry
Platform: UNKNOWN
Classifier: Programming Language :: Python :: 3
Classifier: License :: OSI Approved :: MIT License
Classifier: Operating System :: OS Independent
License-File: LICENSE.txt
Requires-Dist: sentry-sdk (>=1.5.5)
